agentml/errors.py
agentml/__init__.py
agentml/agentml.py
agentml/constants.py
agentml/logger.py
agentml/common.py
agentml/parser/__init__.py
agentml/parser/element.py
agentml/parser/tags/__init__.py
agentml/parser/tags/tag.py
agentml/parser/tags/redirect.py
agentml/parser/tags/var.py
agentml/parser/tags/condition.py
agentml/parser/tags/random.py
agentml/parser/init/__init__.py
agentml/parser/trigger/__init__.py
agentml/parser/trigger/condition/__init__.py
agentml/parser/trigger/condition/types/user_var.py
agentml/parser/trigger/condition/types/__init__.py
agentml/parser/trigger/condition/types/global_var.py
agentml/parser/trigger/condition/types/topic.py
agentml/parser/trigger/condition/types/type.py
agentml/parser/trigger/condition/types/user.py
agentml/parser/trigger/response/__init__.py
agentml/parser/trigger/response/container.py
agentml/schemas/agentml.rng
agentml/schemas/agentml.xsd
agentml/schemas/tags/var.rng
agentml/schemas/tags/condition.rng
agentml/schemas/tags/star.rng
agentml/schemas/tags/random.rng
agentml/schemas/tags/redirect.rng
agentml/intelligence/emotions.aml
saml/errors.py
saml/__init__.py
saml/constants.py
saml/common.py
saml/saml.py
saml/parser/__init__.py
saml/parser/element.py
saml/schemas/saml.xsd
saml/schemas/saml.rng
saml/schemas/tags/var.rng
saml/schemas/tags/condition.rng
saml/schemas/tags/star.rng
saml/schemas/tags/random.rng
saml/intelligence/emotions.saml
saml/intelligence/__init__.saml
saml/intelligence/identity.saml
AgentML-0.2a1.dist-info/METADATA
AgentML-0.2a1.dist-info/metadata.json
AgentML-0.2a1.dist-info/DESCRIPTION.rst
AgentML-0.2a1.dist-info/WHEEL
AgentML-0.2a1.dist-info/RECORD
AgentML-0.2a1.dist-info/top_level.txt
