Metadata-Version: 2.0
Name: AgentML
Version: 0.2a1
Summary: An XML dialect for creating natural language software agents
Home-page: https://github.com/FujiMakoto/AgentML
Author: Makoto Fujimoto
Author-email: makoto@makoto.io
License: MIT
Keywords: bot,chatbot,chatterbot,ai,aiml,rivescript
Platform: UNKNOWN
Classifier: Development Status :: 3 - Alpha
Classifier: Intended Audience :: Developers
Classifier: License :: OSI Approved :: MIT License
Classifier: Natural Language :: English
Classifier: Programming Language :: Python :: 3.4
Classifier: Topic :: Scientific/Engineering :: Artificial Intelligence
Classifier: Topic :: Text Processing :: Markup :: XML
Requires-Dist: lxml (>=3.4.4,<3.5)
